python_excel2json/__init__.py
python_excel2json/main.py
python_excel2json-0.1.dist-info/LICENSE
python_excel2json-0.1.dist-info/METADATA
python_excel2json-0.1.dist-info/WHEEL
python_excel2json-0.1.dist-info/top_level.txt
python_excel2json-0.1.dist-info/RECORD
