Metadata-Version: 2.1
Name: python-excel2json
Version: 0.1
Summary: Python Excel to Json
Home-page: https://github.com/enzoruiz/python_excel2json
Author: Enzo Ruiz Pelaez
Author-email: enzo.rp.90@gmail.com
License: UNKNOWN
Platform: UNKNOWN
Classifier: Programming Language :: Python :: 3
Classifier: License :: OSI Approved :: MIT License
Classifier: Operating System :: OS Independent
Requires-Dist: xlrd
